qiskit_torch_module/__init__.py
qiskit_torch_module/hybrid_module.py
qiskit_torch_module/quantum_autograd.py
qiskit_torch_module/quantum_module.py
qiskit_torch_module/fast_gradients/__init__.py
qiskit_torch_module/fast_gradients/fast_base/__init__.py
qiskit_torch_module/fast_gradients/fast_base/fast_base_estimator_gradient.py
qiskit_torch_module/fast_gradients/fast_base/fast_estimator_gradient_result.py
qiskit_torch_module/fast_gradients/fast_reverse/__init__.py
qiskit_torch_module/fast_gradients/fast_reverse/fast_reverse_gradient.py
qiskit_torch_module/fast_primitives/__init__.py
qiskit_torch_module/fast_primitives/fast_estimator.py
qiskit_torch_module/fast_primitives/fast_base/__init__.py
qiskit_torch_module/fast_primitives/fast_base/fast_base_estimator.py
qiskit_torch_module/fast_primitives/fast_base/fast_base_primitive.py
qiskit_torch_module/fast_primitives/fast_base/fast_estimator_result.py
qiskit_torch_module/quantum_neural_network/__init__.py
qiskit_torch_module/quantum_neural_network/qnn.py
qiskit_torch_module/quantum_neural_network/utils.py
qiskit_torch_module-1.0.1.dist-info/LICENSE
qiskit_torch_module-1.0.1.dist-info/METADATA
qiskit_torch_module-1.0.1.dist-info/WHEEL
qiskit_torch_module-1.0.1.dist-info/top_level.txt
qiskit_torch_module-1.0.1.dist-info/RECORD
