Metadata-Version: 2.1
Name: qiskit-torch-module
Version: 1.0.1
Summary: Qiskit-Torch-Module: Fast Prototyping of Quantum Neural Networks
Home-page: https://github.com/nicomeyer96/qiskit-torch-module
Author: Fraunhofer IIS
Author-email: nico.meyer@iis.fraunhofer.de
License: Apache License 2.0
Classifier: Programming Language :: Python :: 3
Classifier: License :: OSI Approved :: Apache Software License
Classifier: Operating System :: OS Independent
Requires-Python: ~=3.12
License-File: LICENSE
Requires-Dist: qiskit ~=1.0.0
Requires-Dist: qiskit-algorithms ~=0.3.0
Requires-Dist: torch ~=2.2.1
Requires-Dist: threadpoolctl ~=3.3.0
